prms_python/__init__.py
prms_python/data.py
prms_python/optimizer.py
prms_python/parameters.py
prms_python/scenario.py
prms_python/simulation.py
prms_python/util.py
prms_python/models/lbcd/control
prms_python/models/lbcd/data
prms_python/models/lbcd/parameters
prms_python/scripts/__init__.py
prms_python/scripts/prmspy.py
prms_python-1.0.1.dist-info/METADATA
prms_python-1.0.1.dist-info/RECORD
prms_python-1.0.1.dist-info/WHEEL
prms_python-1.0.1.dist-info/entry_points.txt
prms_python-1.0.1.dist-info/top_level.txt
test/test_prms_python.py
