Metadata-Version: 2.1
Name: prms-python
Version: 1.0.1
Summary: A Python package with tools for the PRMS hydrologic model.
Home-page: https://github.com/JohnVolk/PRMS-Python
Author: John Volk and Matthew Turner
Author-email: jmvolk@unr.edu
License: BSD3
Platform: Windows
Platform: Linux
Platform: Mac OS X
Classifier: License :: OSI Approved :: BSD License
Classifier: Programming Language :: Python :: 2.7
Classifier: Programming Language :: Python :: 3.4
Classifier: Programming Language :: Python :: 3.5
Classifier: Programming Language :: Python :: 3.6
Classifier: Programming Language :: Python :: 3.7
Classifier: Environment :: Console
Classifier: Development Status :: 4 - Beta
Classifier: Topic :: Scientific/Engineering
Classifier: Intended Audience :: Science/Research
Requires-Dist: click (==6.6)
Requires-Dist: numpy (>=1.11.1)
Requires-Dist: pandas (>=0.18.1)
Requires-Dist: matplotlib (>=1.5.1)
